Metadata-Version: 2.1
Name: pyate
Version: 0.5.5
Summary: PYthon Automated Term Extraction
Home-page: https://github.com/kevinlu1248/pyate
Author: Kevin Lu
Author-email: kevinlu1248@gmail.com
License: MIT
Download-URL: https://github.com/kevinlu1248/pyate/archive/0.4.tar.gz
Keywords: nlp,python3,spacy,term_extraction
Platform: UNKNOWN
Classifier: Development Status :: 3 - Alpha
Classifier: Intended Audience :: Developers
Classifier: Topic :: Software Development :: Build Tools
Classifier: License :: OSI Approved :: MIT License
Classifier: Programming Language :: Python :: 3
